{
  "id": "1968dovd",
  "slug": "1968dovd",
  "title": "Arch 1968dovd",
  "author": "",
  "category": "other",
  "language": "uk",
  "year": 0,
  "description": "Вибачте, але \"Arch 1968dovd\" — це не розпізнана назва українського видання. Спробуйте перевірити назву книги, автора або навести інші деталі для точної ідентифікації.",
  "shortDescription": "Вибачте, але \"Arch 1968dovd\" — це не розпізнана назва українського видання.",
  "coverImage": "/covers/1968dovd.jpg",
  "files": [
    {
      "format": "epub",
      "filename": "arch_1968dovd__Dovidnyk_ukrainskykh_prizvyshch.epub",
      "fileDir": "Д",
      "sizeMb": 0.3
    }
  ],
  "isFeatured": false,
  "isNewArrival": true,
  "downloadCount": 0,
  "rating": 0,
  "addedAt": "2026-04-22",
  "subcategory": "foreign-language"
}