{
  "id": "20210131-20210131-1423",
  "slug": "20210131-20210131-1423",
  "title": "Arch 20210131 20210131 1423",
  "author": "",
  "category": "other",
  "language": "uk",
  "year": 0,
  "description": "Вибачте, але надані дані недостатні для створення опису. У вас є тільки архівна позначка без назви книги, автора чи категорії, яка б дозволила зрозуміти зміст. Потрібна конкретна інформація про твір.",
  "shortDescription": "Вибачте, але надані дані недостатні для створення опису. У вас є тільки архівна позначка без назви книги, автора чи категорії, яка б дозволила зрозуміти зміст.",
  "coverImage": "/covers/20210131-20210131-1423.jpg",
  "files": [
    {
      "format": "epub",
      "filename": "arch_20210131_20210131_1423__Navishcho_Ya_Narodylasia_Divchynkoiu.Gabi_Kopp.epub",
      "fileDir": "Н",
      "sizeMb": 0.16
    }
  ],
  "isFeatured": false,
  "isNewArrival": true,
  "downloadCount": 0,
  "rating": 0,
  "addedAt": "2026-04-22"
}