{
  "id": "amtm-8431",
  "slug": "amtm-8431",
  "title": "АМтм",
  "author": "Юрко Іздрик",
  "category": "literature-foreign",
  "language": "uk",
  "year": 2004,
  "description": "AM™ — книга, яка пасуватиме не лише шанувальникам високочолого письма, а й ентузіастам хитромудрих сюжетних колізій. Із запропонованих Автором текстових пазлів кожен Читач зможе укласти власну Історію. AM™ — традиційний роман в новелах, а водночас — літературний ребус, друкований кубик-рубик, словесна гра, інтелектуальний ендшпіль і просто доміно. _________ В авторській редакції _________ Дизайнер обкладинки Юрій Іздрик",
  "shortDescription": "AM™ — книга, яка пасуватиме не лише шанувальникам високочолого письма, а й ентузіастам хитромудрих сюжетних колізій. Із запропонованих Автором текстових пазлів кожен Читач зможе укласти власну Історію",
  "coverImage": "/covers/placeholder.jpg",
  "files": [
    {
      "format": "epub",
      "filename": "amtm-8431__AMtm.epub",
      "fileDir": "А",
      "sizeMb": 0.7
    },
    {
      "format": "fb2",
      "filename": "amtm-8431__AMtm__amtm.fb2",
      "fileDir": "А",
      "sizeMb": 1.1
    }
  ],
  "isFeatured": false,
  "isNewArrival": false,
  "downloadCount": 0,
  "rating": 0,
  "addedAt": "2024-01-01",
  "subcategory": "novels"
}