{
  "id": "bagryana-koroleva-16223",
  "slug": "bagryana-koroleva-16223",
  "title": "Багряна королева",
  "author": "Вікторія Авеярд",
  "category": "fantasy",
  "language": "en",
  "year": null,
  "description": "Сімнадцятирічній Марі Барров усе життя не щастить. Вона народилася в радіоактивній пустці постапокаліптичного світу, та ще й у його найупослідженішому прошарку багряних. Її ось-ось відправлять на нескінченну війну, з якої більшість не повертається, та ще й найкращого друга не вдається порятувати від цієї долі. Мара не належить до панівної еліти з надприродними здібностями, вона надбала небезпечних ворогів, які впевнені: ця дівчина може зруйнувати усталений світовий лад. Несподівано для себе Мара опиняється у вирі політичних інтриг і таємного руху спротиву й незабаром розуміє, що саме вона може змінити хід історії. Вона ні в чому не може бути певною, крім того, що революція неминуча, а зрадити може кожен.",
  "shortDescription": "Сімнадцятирічній Марі Барров усе життя не щастить. Вона народилася в радіоактивній пустці постапокаліптичного світу, та ще й у його найупослідженішому прошарку багряних. Її ось-ось відправлять на неск",
  "coverImage": "/covers/bagryana-koroleva-16223.jpg",
  "files": [
    {
      "format": "epub",
      "filename": "bagryana-koroleva-16223__Bahriana_koroleva.epub",
      "fileDir": "Б",
      "sizeMb": 0.7
    },
    {
      "format": "fb2",
      "filename": "bagryana-koroleva-16223__Bahriana_koroleva__bagryana-koroleva.fb2",
      "fileDir": "Б",
      "sizeMb": 1.5
    }
  ],
  "isFeatured": false,
  "isNewArrival": false,
  "downloadCount": 0,
  "rating": 0,
  "addedAt": "2024-01-01",
  "subcategory": "fantasy"
}