{
  "id": "bdsm-bud-dobroyu-sluhnyanoyu-i-miloyu-34010",
  "slug": "bdsm-bud-dobroyu-sluhnyanoyu-i-miloyu-34010",
  "title": "BDSM. Bud dobroiu slukhnianoiu i myloiu",
  "author": "Невідомий автор",
  "authorSlug": "nevidomyi-avtor",
  "description": "<p>«BDSM. Bud dobroiu slukhnianoiu i myloiu» — книга автора Невідомий автор.</p>",
  "shortDescription": "«BDSM. Bud dobroiu slukhnianoiu i myloiu» — книга автора Невідомий автор.",
  "category": "other",
  "tags": [],
  "language": "uk",
  "year": 0,
  "coverImage": "/covers/bdsm-bud-dobroyu-sluhnyanoyu-i-miloyu-34010.jpg",
  "files": [
    {
      "format": "fb2",
      "filename": "bdsm-bud-dobroyu-sluhnyanoyu-i-miloyu-34010__BDSM._Bud_dobroiu_slukhnianoiu_i_myloiu__bdsm-bud-dobroyu-sluhnyanoyu-i-miloyu.fb2",
      "sizeMb": 1.5
    }
  ],
  "isFeatured": false,
  "isNewArrival": false,
  "downloadCount": 0,
  "rating": 0,
  "addedAt": "2026-04-09",
  "metaTitle": "BDSM. Bud dobroiu slukhnianoiu i myloiu — Невідомий автор | Завантажити FB2",
  "metaDescription": "Завантажте «BDSM. Bud dobroiu slukhnianoiu i myloiu» автора Невідомий автор безкоштовно у форматах FB2."
}