{
  "id": "bilosnizhka-ta-semero-gnomiv",
  "slug": "bilosnizhka-ta-semero-gnomiv",
  "title": "Білосніжка та семеро гномів",
  "author": "Unknown",
  "authorSlug": "unknown",
  "description": "<p>Улюблена дитяча казка у бездоганному «абабагаламазькому» викладі. ISBN 966-7047-50-4 © «А-БА-БА-ГА-ЛА-МА-ГА», 2006 Ілюстрації © Оксана Ігнащенко, 1997, 2006 Переказ І.Малковича за перекладом Віталія Коротича</p>",
  "shortDescription": "Улюблена дитяча казка у бездоганному «абабагаламазькому» викладі. ISBN 966-7047-50-4 © «А-БА-БА-ГА-ЛА-МА-ГА», 2006 Ілюстрації © Оксана Ігнащенко, 1997, 2006 Переказ І.",
  "category": "other",
  "tags": [],
  "language": "uk",
  "year": 0,
  "coverImage": "/covers/bilosnizhka-ta-semero-gnomiv.jpg",
  "files": [
    {
      "format": "epub",
      "filename": "bilosnizhka-ta-semero-gnomiv - Білосніжка та семеро гномів.epub",
      "sizeMb": 2.1
    },
    {
      "format": "fb2",
      "filename": "bilosnizhka-ta-semero-gnomiv - Білосніжка та семеро гномів__Bilosnizhka ta siemiero ghnomiv - Nievidomii.fb2",
      "sizeMb": 3.0
    }
  ],
  "isFeatured": false,
  "isNewArrival": false,
  "downloadCount": 0,
  "rating": 0,
  "addedAt": "2026-04-09",
  "metaTitle": "Білосніжка та семеро гномів — Unknown | Завантажити EPUB, FB2",
  "metaDescription": "Завантажте «Білосніжка та семеро гномів» автора Unknown безкоштовно у форматах EPUB, FB2."
}