{
  "id": "cnx-org-col10539",
  "slug": "cnx-org-col10539",
  "title": "Курс «Сучасні медіасистеми і політичні комунікації»",
  "author": "Видавництво Наука",
  "category": "other",
  "language": "uk",
  "year": 0,
  "description": "«Суча́сні медіасисте́ми: три моде́лі відно́син ЗМІ та полі́тики» — книга про дослідження сучасних ЗМІ та їхнього функціонування в суспільстві Comparing Media Systems: Three Models of Media and Politics (Communication, Society and Politics). Бібліографічні дані українського видання: Галлін Деніел С., Манчіні Паоло. Сучасні медіасистеми: три моделі відносин ЗМІ та політики / Переклад з англ. О.",
  "shortDescription": "«Суча́сні медіасисте́ми: три моде́лі відно́син ЗМІ та полі́тики» — книга про дослідження сучасних ЗМІ та їхнього функціонування в суспільстві Comparing Media...",
  "coverImage": "/covers/cnx-org-col10539.jpg",
  "files": [
    {
      "format": "epub",
      "filename": "arch_cnx-org-col10539__Kurs_Suchasni_mediasystemy_i_politychni_komunikatsii.epub",
      "fileDir": "К",
      "sizeMb": 0.05
    }
  ],
  "isFeatured": false,
  "isNewArrival": true,
  "downloadCount": 0,
  "rating": 0,
  "addedAt": "2026-04-22",
  "subcategory": "uncategorized"
}