{
  "id": "diasp-20872",
  "slug": "diasp-20872",
  "title": "Пеленський Є. Українська читанка для 3 кляси",
  "author": "Євген Ю. Пеленський",
  "category": "other",
  "language": "uk",
  "year": 0,
  "description": "Євген-Юлій Пеленський (3 січня 1908, с. Конюхів, повіт Стрий, Галичина, Австро-Угорщина, нині Стрийський район Львівської обл. — 25 вересня 1956, Сідней, Австралія) — український бібліограф, літературознавець, музеєзнавець, видавець, педагог, упорядник книжок, автор передмов і приміток до книг, громадський діяч, пластун.",
  "shortDescription": "Євген-Юлій Пеленський (3 січня 1908, с. Конюхів, повіт Стрий, Галичина, Австро-Угорщина, нині Стрийський район Львівської обл.",
  "coverImage": "/covers/placeholder.jpg",
  "files": [
    {
      "format": "pdf",
      "filename": "diasp_20872__Pelenskyi_Ye._Ukrainska_chytanka_dlia_3_kliasy.pdf",
      "fileDir": "П",
      "sizeMb": 0.59
    }
  ],
  "isFeatured": false,
  "isNewArrival": true,
  "downloadCount": 0,
  "rating": 0,
  "addedAt": "2026-04-22"
}