{
  "id": "diasp-31420",
  "slug": "diasp-31420",
  "title": "Забіла Н. Перший крок",
  "author": "Наталя Забіла",
  "category": "other",
  "language": "uk",
  "year": 0,
  "description": "Ната́ля Льв́івна Забі́ла (20 лютого (5 березня) 1903(19030305), Санкт-Петербург — 6 лютого 1985, Київ) — українська поетеса, прозаїкиня, драматургиня.",
  "shortDescription": "Ната́ля Льв́івна Забі́ла (20 лютого (5 березня) 1903(19030305), Санкт-Петербург — 6 лютого 1985, Київ) — українська поетеса, прозаїкиня, драматургиня.",
  "coverImage": "/covers/diasp-31420.jpg",
  "files": [
    {
      "format": "pdf",
      "filename": "diasp_31420__Zabila_N._Pershyi_krok.pdf",
      "fileDir": "З",
      "sizeMb": 7.93
    }
  ],
  "isFeatured": false,
  "isNewArrival": true,
  "downloadCount": 0,
  "rating": 0,
  "addedAt": "2026-04-22",
  "subcategory": "uncategorized"
}