{
  "id": "faride-26175",
  "slug": "faride-26175",
  "title": "Фаріде. Роман-апокриф",
  "author": "Роздобудько Ірен",
  "category": "ukr-literature",
  "language": "uk",
  "year": null,
  "description": "Іре́н Віта́ліївна Роздобу́дько (нар. 3 листопада 1962, Донецьк) — українська письменниця, ілюстраторка та сценаристка, викладачка кінодраматургії. До початку письменницької та сценарної кар'єри видала кілька російськомовних збірок поезій та працювала журналісткою.",
  "shortDescription": "Іре́н Віта́ліївна Роздобу́дько (нар. 3 листопада 1962, Донецьк) — українська письменниця, ілюстраторка та сценаристка, викладачка кінодраматургії.",
  "coverImage": "/covers/placeholder.jpg",
  "files": [
    {
      "format": "epub",
      "filename": "faride-26175__Faride.epub",
      "fileDir": "Ф",
      "sizeMb": 0.3
    },
    {
      "format": "fb2",
      "filename": "faride-26175__Faride__faride.fb2",
      "fileDir": "Ф",
      "sizeMb": 1.3
    }
  ],
  "isFeatured": false,
  "isNewArrival": false,
  "downloadCount": 0,
  "rating": 0,
  "addedAt": "2024-01-01"
}