{
  "id": "krila-koloru-hmar-23061",
  "slug": "krila-koloru-hmar-23061",
  "title": "Крила кольору хмар",
  "author": "Дара Корній",
  "category": "fantasy",
  "language": "uk",
  "year": null,
  "description": "День і ніч, світло і темрява, життя і смерть… Мабуть, світ взагалі існує завдяки тонкій рівновазі між двома боками — темним і світлим. Та в зламні моменти цей баланс може порушитися, і тоді доля світу завмирає на шальках терезів… Зеленоока львів’янка Ада — з роду сірих янголів, які існують на межі між добром і злом. Та настає час, коли потрібно зробити вибір. Вона може урівноважити темні і світлі сили або схилити ваги на чийсь бік… Усе залежить від того, який колір крил вона обере.",
  "shortDescription": "День і ніч, світло і темрява, життя і смерть… Мабуть, світ взагалі існує завдяки тонкій рівновазі між двома боками — темним і світлим. Та в зламні моменти цей баланс може порушитися, і тоді доля світу",
  "coverImage": "/covers/krila-koloru-hmar-23061.jpg",
  "files": [
    {
      "format": "epub",
      "filename": "krila-koloru-hmar-23061__Kryla_koloru_khmar.epub",
      "fileDir": "К",
      "sizeMb": 0.7
    },
    {
      "format": "fb2",
      "filename": "krila-koloru-hmar-23061__Kryla_koloru_khmar__krila-koloru-hmar.fb2",
      "fileDir": "К",
      "sizeMb": 1.3
    }
  ],
  "isFeatured": false,
  "isNewArrival": false,
  "downloadCount": 0,
  "rating": 0,
  "addedAt": "2024-01-01",
  "subcategory": "fantasy"
}