{
  "id": "lyudina-v-labirinti-30145",
  "slug": "lyudina-v-labirinti-30145",
  "title": "Донато Каррізі_Слідство Міли Васкес. Книга 3. Людина в лабіринті",
  "author": "Невідомий автор",
  "category": "other",
  "language": "en",
  "year": null,
  "description": "Вона прокидається в лікарняній палаті без вікон й усвідомлює, що нічого не пам’ятає про власне минуле. Може, це не реальність, а жорстока гра? Та доктор Грін терпляче пояснює: її звуть Саманта, її викрали дорогою до школи, а тепер, схоже, вона втекла з полону і може допомогти покарати злочинця. Велике дзеркало в палаті розкриває страшну правду: з моменту зникнення Саманти минуло аж 15 років. Але вона здатна розповісти Грінові тільки про моторошний лабіринт та його правила. Приватний детектив Бруно, який розслідував зникнення Саманти, дізнається про її звільнення. Обмежений у часі через серйозну хворобу, він вирішує повернутися до справи, яка не дає йому спокою навіть на порозі смерті…",
  "shortDescription": "Вона прокидається в лікарняній палаті без вікон й усвідомлює, що нічого не пам’ятає про власне минуле. Може, це не реальність, а жорстока гра? Та доктор Грін терпляче пояснює: її звуть Саманта, її вик",
  "coverImage": "/covers/lyudina-v-labirinti-30145.jpg",
  "files": [
    {
      "format": "epub",
      "filename": "lyudina-v-labirinti-30145__Liudyna_v_labirynti.epub",
      "fileDir": "Л",
      "sizeMb": 0.9
    },
    {
      "format": "fb2",
      "filename": "lyudina-v-labirinti-30145__Liudyna_v_labirynti__lyudina-v-labirinti.fb2",
      "fileDir": "Л",
      "sizeMb": 1.6
    }
  ],
  "isFeatured": false,
  "isNewArrival": false,
  "downloadCount": 0,
  "rating": 0,
  "addedAt": "2024-01-01",
  "subcategory": "uncategorized"
}