{
  "id": "myshkova-kasha",
  "slug": "myshkova-kasha",
  "title": "Мишкова каша",
  "author": "Микола Носов",
  "authorSlug": "mykola-nosov",
  "description": "<p>Повний текст \"Мишкова каша\" (автор: Носов Микола Миколайович) з Бібліотеки Української Літератури УкрЛіб</p>",
  "shortDescription": "Повний текст \"Мишкова каша\" (автор: Носов Микола Миколайович) з Бібліотеки Української Літератури УкрЛіб",
  "category": "other",
  "tags": [],
  "language": "uk",
  "year": 0,
  "coverImage": "/covers/myshkova-kasha.jpg",
  "files": [
    {
      "format": "epub",
      "filename": "myshkova-kasha - Мишкова каша.epub",
      "sizeMb": 0.0
    }
  ],
  "isFeatured": false,
  "isNewArrival": false,
  "downloadCount": 0,
  "rating": 0,
  "addedAt": "2026-04-09",
  "metaTitle": "Мишкова каша — Микола Носов | Завантажити EPUB",
  "metaDescription": "Завантажте «Мишкова каша» автора Микола Носов безкоштовно у форматах EPUB."
}