{
  "id": "nastane-den-zakinchitsya-vijna-14743",
  "slug": "nastane-den-zakinchitsya-vijna-14743",
  "title": "Настане день, закінчиться війна…",
  "author": "Петро Михайлович Лущик",
  "category": "ukr-literature",
  "language": "uk",
  "year": 2015,
  "description": "Роман «Настане день, закінчиться війна…» здобув третю премію на «Коронації слова-2015». Події цієї сімейної хроніки відбуваються в галицькому селі Кам’янка Лісна упродовж першої половини ХХ століття. В центрі роману – доля трьох братів Засмужних, хліборобів, людей суто мирної праці, яким, однак, доводиться воювати. Війни не оминули нікого: Теодор пройшов страшний табір Талергоф, Першу світову і війну за незалежність України; зазнав «принад» російського полону Іван; повернувся інвалідом з польсько-української війни наймолодший брат Юрій. Не відпустив молох війни і наступне покоління родини. Проте, незважаючи на тяжкі випробування, Засмужні завжди намагалися зберегти честь і прагнули за будь-яких обставин залишатися людьми.",
  "shortDescription": "Роман «Настане день, закінчиться війна…» здобув третю премію на «Коронації слова-2015». Події цієї сімейної хроніки відбуваються в галицькому селі Кам’янка Лісна упродовж першої половини ХХ століття. ",
  "coverImage": "/covers/nastane-den-zakinchitsya-vijna-14743.jpg",
  "files": [
    {
      "format": "epub",
      "filename": "nastane-den-zakinchitsya-vijna-14743__Nastane_den_zakinchytsia_viina.epub",
      "fileDir": "Н",
      "sizeMb": 0.6
    },
    {
      "format": "fb2",
      "filename": "nastane-den-zakinchitsya-vijna-14743__Nastane_den_zakinchytsia_viina__nastane-den-zakinchitsya-vijna.fb2",
      "fileDir": "Н",
      "sizeMb": 1.2
    }
  ],
  "isFeatured": false,
  "isNewArrival": false,
  "downloadCount": 0,
  "rating": 0,
  "addedAt": "2024-01-01"
}