{
  "id": "nebo-i-peklo-16239",
  "slug": "nebo-i-peklo-16239",
  "title": "Небо і Пекло",
  "author": "Олдос Гакслі",
  "category": "history",
  "language": "uk",
  "year": null,
  "description": "",
  "shortDescription": "",
  "coverImage": "/covers/nebo-i-peklo-16239.jpg",
  "files": [
    {
      "format": "epub",
      "filename": "nebo-i-peklo-16239__Nebo_i_Peklo.epub",
      "fileDir": "Н",
      "sizeMb": 0.8
    },
    {
      "format": "fb2",
      "filename": "nebo-i-peklo-16239__Nebo_i_Peklo__nebo-i-peklo.fb2",
      "fileDir": "Н",
      "sizeMb": 1.0
    }
  ],
  "isFeatured": false,
  "isNewArrival": false,
  "downloadCount": 0,
  "rating": 0,
  "addedAt": "2024-01-01"
}