{
  "id": "obitnitsya-23216",
  "slug": "obitnitsya-23216",
  "title": "Обітниця",
  "author": "Володимир Лис",
  "category": "ukr-literature",
  "language": "uk",
  "year": null,
  "description": "Володимир Савович Лис (нар. 26 жовтня 1950, хутір поблизу села Згорани, Волинська область) — український журналіст, драматург, письменник. Відомий також як народний синоптик.",
  "shortDescription": "Володимир Савович Лис (нар. 26 жовтня 1950, хутір поблизу села Згорани, Волинська область) — український журналіст, драматург, письменник.",
  "coverImage": "/covers/obitnitsya-23216.jpg",
  "files": [
    {
      "format": "epub",
      "filename": "obitnitsya-23216__Obitnytsia.epub",
      "fileDir": "О",
      "sizeMb": 0.6
    },
    {
      "format": "fb2",
      "filename": "obitnitsya-23216__Obitnytsia__obitnitsya.fb2",
      "fileDir": "О",
      "sizeMb": 1.2
    }
  ],
  "isFeatured": false,
  "isNewArrival": false,
  "downloadCount": 0,
  "rating": 0,
  "addedAt": "2024-01-01"
}