{
  "id": "opivnich-z-toboyu-22224",
  "slug": "opivnich-z-toboyu-22224",
  "title": "Опівніч з тобою",
  "author": "Клер Осонгко",
  "category": "science",
  "language": "uk",
  "year": null,
  "description": "Це англійськомовна праця про історію ночі як соціального явища, де Осонгко досліджує, як люди пережили й переживають темряву крізь призму культури, технологій та влади.",
  "shortDescription": "Це англійськомовна праця про історію ночі як соціального явища, де Осонгко досліджує, як люди пережили й переживають темряву крізь призму культури, технологій...",
  "coverImage": "/covers/opivnich-z-toboyu-22224.jpg",
  "files": [
    {
      "format": "epub",
      "filename": "opivnich-z-toboyu-22224__Opivnich_z_toboiu.epub",
      "fileDir": "О",
      "sizeMb": 5.3
    },
    {
      "format": "fb2",
      "filename": "opivnich-z-toboyu-22224__Opivnich_z_toboiu__opivnich-z-toboyu.fb2",
      "fileDir": "О",
      "sizeMb": 9.7
    }
  ],
  "isFeatured": false,
  "isNewArrival": false,
  "downloadCount": 0,
  "rating": 0,
  "addedAt": "2024-01-01"
}