{
  "id": "p-yata-pora-26725",
  "slug": "p-yata-pora-26725",
  "title": "The Fifth Season",
  "author": "Nora Kate Jemisin",
  "category": "history",
  "language": "uk",
  "year": null,
  "description": "Nora Keita Jemisin (born September 19, 1972) is an American science fiction and fantasy writer. Her fiction includes a wide range of themes, notably cultural conflict and oppression. Her debut novel, The Hundred Thousand Kingdoms (2010), and the subsequent books in her Inheritance Trilogy received critical acclaim.",
  "shortDescription": "Nora Keita Jemisin (born September 19, 1972) is an American science fiction and fantasy writer.",
  "coverImage": "/covers/p-yata-pora-26725.jpg",
  "files": [
    {
      "format": "epub",
      "filename": "p-yata-pora-26725__Piata_pora.epub",
      "fileDir": "П",
      "sizeMb": 0.7
    },
    {
      "format": "fb2",
      "filename": "p-yata-pora-26725__Piata_pora__p-yata-pora.fb2",
      "fileDir": "П",
      "sizeMb": 1.8
    }
  ],
  "isFeatured": false,
  "isNewArrival": false,
  "downloadCount": 0,
  "rating": 0,
  "addedAt": "2024-01-01"
}