{
  "id": "piknik-na-lodu-22368",
  "slug": "piknik-na-lodu-22368",
  "title": "Пікнік на льоду",
  "author": "Андрій Курков",
  "category": "history",
  "language": "uk",
  "year": null,
  "description": "Головний герой роману «Пікнік на льоду» — журналіст Віктор Золотарьов — отримує незвичайне завдання від однієї провідної газети: писати некрологи про відомих впливових людей, які... поки ще живі. Поступово він розуміє, що став учасником серйозної гри якихось тіньових структур, вийти з якої живим практично неможливо...",
  "shortDescription": "Головний герой роману «Пікнік на льоду» — журналіст Віктор Золотарьов — отримує незвичайне завдання від однієї провідної газети: писати некрологи про відомих впливових людей, які... поки ще живі. Пост",
  "coverImage": "/covers/piknik-na-lodu-22368.jpg",
  "files": [
    {
      "format": "epub",
      "filename": "piknik-na-lodu-22368__Piknik_na_lodu.epub",
      "fileDir": "П",
      "sizeMb": 1.1
    },
    {
      "format": "fb2",
      "filename": "piknik-na-lodu-22368__Piknik_na_lodu__piknik-na-lodu.fb2",
      "fileDir": "П",
      "sizeMb": 0.9
    }
  ],
  "isFeatured": false,
  "isNewArrival": false,
  "downloadCount": 0,
  "rating": 0,
  "addedAt": "2024-01-01"
}