{
  "id": "pisochnij-cholovik-28022",
  "slug": "pisochnij-cholovik-28022",
  "title": "Pisochnyi cholovik",
  "author": "Невідомий автор",
  "category": "other",
  "language": "uk",
  "year": null,
  "description": "Невідомі твір, ймовірно фольклорного походження, про людину з піску — персонажа, що міг символізувати марність, тимчасовість або магічні трансформації в українській традиційній культурі. Твір зберігся в усній формі та відображає архаїчні міфологічні уявлення.",
  "shortDescription": "Невідомі твір, ймовірно фольклорного походження, про людину з піску — персонажа, що міг символізувати марність, тимчасовість або магічні трансформації в...",
  "coverImage": "/covers/pisochnij-cholovik-28022.jpg",
  "files": [
    {
      "format": "epub",
      "filename": "pisochnij-cholovik-28022__Pisochnyi_cholovik.epub",
      "fileDir": "П",
      "sizeMb": 0.4
    },
    {
      "format": "fb2",
      "filename": "pisochnij-cholovik-28022__Pisochnyi_cholovik__pisochnij-cholovik.fb2",
      "fileDir": "П",
      "sizeMb": 1.3
    }
  ],
  "isFeatured": false,
  "isNewArrival": false,
  "downloadCount": 0,
  "rating": 0,
  "addedAt": "2024-01-01",
  "subcategory": "foreign-language"
}