{
  "id": "pomaranchevij-sad-695",
  "slug": "pomaranchevij-sad-695",
  "title": "Помаранчевий сад",
  "author": "Ларрі Трамбле",
  "category": "literature-foreign",
  "language": "uk",
  "year": null,
  "description": "Коли Амед плаче, Азіз плаче теж. Коли Азіз сміється, Амед сміється також. Ці брати-близнюки могли б мирно жити в затінку помаранчевих дерев. Але снаряд перетинає небо, вбиває їхніх бабусю і дідуся. Війна вривається в їхнє дитинство і розділяє їх. З’являються чоловіки, які вимагають помститися за кров ближніх. Амед чи Азіз – комусь із них доведеться принести найбільшу з можливих жертв. І всі віддають шану мученику – як мертві, так і ті, що залишилися. Даючи читачеві можливість вирішувати, хто є чистим душею, брехуном, героєм-фанатиком, цей твір, що став уже невід’ємною частиною квебекської літератури, що є водночас на часі і поза часом, сповнений потужної сили великих трагедій і ліризму легенд пустелі. Усі права застережені . Жодну частину цього видання не можна переви­да­ва­ти, перекладати, зберігати в пошукових системах або передавати у будь-якій формі та будь-яким засобом (електронним, механічним, фотокопіюванням або іншим) без попередньої письмової згоди на це ТОВ «Видавництво Анетти Антоненко». ISBN 978-617-7654-02-4 © Larry Tremblay and Éditions Alto, 2013 This edition is published by arrangement with Alto Editions in conjunction with its duly appointed agent L’Autre agence, Paris, France. All rights reserved © Ростислав Нємцев, український переклад, 2018 © «Видавництво Анетти Антоненко», 2018",
  "shortDescription": "Коли Амед плаче, Азіз плаче теж. Коли Азіз сміється, Амед сміється також. Ці брати-близнюки могли б мирно жити в затінку помаранчевих дерев. Але снаряд перетинає небо, вбиває їхніх бабусю і дідуся. Ві",
  "coverImage": "/covers/placeholder.jpg",
  "files": [
    {
      "format": "epub",
      "filename": "pomaranchevij-sad-695__Pomaranchevyi_sad.epub",
      "fileDir": "П",
      "sizeMb": 0.2
    },
    {
      "format": "fb2",
      "filename": "pomaranchevij-sad-695__Pomaranchevyi_sad__pomaranchevij-sad.fb2",
      "fileDir": "П",
      "sizeMb": 0.3
    }
  ],
  "isFeatured": false,
  "isNewArrival": false,
  "downloadCount": 0,
  "rating": 0,
  "addedAt": "2024-01-01",
  "subcategory": "novels"
}