{
  "id": "samostiyna-ukraina",
  "slug": "samostiyna-ukraina",
  "title": "Arch Samostiyna Ukraina",
  "author": "",
  "category": "other",
  "language": "uk",
  "year": 0,
  "description": "\"Arch\" — діаспорний часопис українців у Канаді, присвячений питанням незалежності й національного відродження. Видання відстоювало ідею суверенної України в період, коли вона була радянською республікою.",
  "shortDescription": "\"Arch\" — діаспорний часопис українців у Канаді, присвячений питанням незалежності й національного відродження.",
  "coverImage": "/covers/samostiyna-ukraina.jpg",
  "files": [
    {
      "format": "epub",
      "filename": "arch_Samostiyna_Ukraina__Zhurnal_Samostiina_Ukraina_1948-1999.epub",
      "fileDir": "Ж",
      "sizeMb": 18.94
    }
  ],
  "isFeatured": false,
  "isNewArrival": true,
  "downloadCount": 0,
  "rating": 0,
  "addedAt": "2026-04-22",
  "subcategory": "foreign-language"
}