{
  "id": "spaliti-hrom-19904",
  "slug": "spaliti-hrom-19904",
  "title": "Вільям Ґібсон. Спалити хром (2022)",
  "author": "Вільям Ґібсон",
  "category": "fiction",
  "language": "uk",
  "year": null,
  "description": "Вільям Ґібсон справедливо вважається батьком кіберпанку, а багато його передбачень, зроблених ще на початку 80-х років минулого сторіччя, лише зараз починають справджуватися або ж невдовзі стануть реальністю, оскільки вже тепер зрозуміло, що наш світ, так чи інакше, але таки рухається приблизно за сценарієм Ґібсона. «Спалити Хром» — це авторська збірка оповідань, що сформували класику кіберпанку і дають найкраще уявлення про цей жанр наукової фантастики. Глобальна мережа Інтернет, що ось-ось перетвориться на той самий Кіберпростір, високотехнологічні комунікації, в лабіринтах яких точаться інформаційні війни, інформація як найбільша цінність і водночас найпотужніша зброя новітнього часу, віртуальна реальність, явні й приховані війни корпорацій за панування над новітніми технологіями, а отже, і над світом, модифіковані людські тіла і свідомості нового рівня, штучні інтелекти й етичні питання, пов'язані з їхнім існуванням, — ми вже майже вступили в колись описаний Ґібсоном світ, тож корисно зазирнути ще трохи далі й дізнатися, що чекає на людство за найближчим поворотом його історії. Саме таку можливість і дає нам ця непересічна класика кіберпанку.",
  "shortDescription": "Вільям Ґібсон справедливо вважається батьком кіберпанку, а багато його передбачень, зроблених ще на початку 80-х років минулого сторіччя, лише зараз починають справджуватися або ж невдовзі стануть реа",
  "coverImage": "/covers/spaliti-hrom-19904.jpg",
  "files": [
    {
      "format": "epub",
      "filename": "spaliti-hrom-19904__Spalyty_khrom.epub",
      "fileDir": "С",
      "sizeMb": 0.4
    },
    {
      "format": "fb2",
      "filename": "spaliti-hrom-19904__Spalyty_khrom__spaliti-hrom.fb2",
      "fileDir": "С",
      "sizeMb": 0.5
    }
  ],
  "isFeatured": false,
  "isNewArrival": false,
  "downloadCount": 0,
  "rating": 0,
  "addedAt": "2024-01-01"
}