{
  "id": "vakhanky",
  "slug": "vakhanky",
  "title": "Вакханки",
  "author": "Евріпід",
  "authorSlug": "evripid",
  "description": "<p>Повний текст \"Вакханки\" (автор: Евріпід) з Бібліотеки Української Літератури УкрЛіб</p>",
  "shortDescription": "Повний текст \"Вакханки\" (автор: Евріпід) з Бібліотеки Української Літератури УкрЛіб",
  "category": "other",
  "tags": [],
  "language": "uk",
  "year": 0,
  "coverImage": "/covers/vakhanky.jpg",
  "files": [
    {
      "format": "epub",
      "filename": "vakhanky - Вакханки.epub",
      "sizeMb": 0.0
    }
  ],
  "isFeatured": false,
  "isNewArrival": false,
  "downloadCount": 0,
  "rating": 0,
  "addedAt": "2026-04-09",
  "metaTitle": "Вакханки — Евріпід | Завантажити EPUB",
  "metaDescription": "Завантажте «Вакханки» автора Евріпід безкоштовно у форматах EPUB."
}