{
  "id": "vovk-ta-semero-kozenyat",
  "slug": "vovk-ta-semero-kozenyat",
  "title": "Vovk ta semero kozeniat",
  "author": "Невідомий автор",
  "authorSlug": "nevidomyi-avtor",
  "description": "<p>«Vovk ta semero kozeniat» — книга автора Невідомий автор.</p>",
  "shortDescription": "«Vovk ta semero kozeniat» — книга автора Невідомий автор.",
  "category": "other",
  "tags": [],
  "language": "uk",
  "year": 0,
  "coverImage": "/covers/vovk-ta-semero-kozenyat.jpg",
  "files": [
    {
      "format": "txt",
      "filename": "vovk-ta-semero-kozenyat__Vovk_ta_semero_kozeniat.txt",
      "sizeMb": 0.0
    }
  ],
  "isFeatured": false,
  "isNewArrival": false,
  "downloadCount": 0,
  "rating": 0,
  "addedAt": "2026-04-09",
  "metaTitle": "Vovk ta semero kozeniat — Невідомий автор | Завантажити TXT",
  "metaDescription": "Завантажте «Vovk ta semero kozeniat» автора Невідомий автор безкоштовно у форматах TXT."
}