{
  "id": "yevpraksiya-11726",
  "slug": "yevpraksiya-11726",
  "title": "Євпраксія",
  "author": "Павло Загребельний",
  "category": "ukr-literature",
  "language": "uk",
  "year": 2013,
  "description": "Події в романі відбуваються на межі ХІ — ХІІ століть. Внучка Ярослава Мудрого київська княжна Євпраксія виходить заміж за Генріха ІV і стає германською імператрицею. Але ж доля молодої жінки складається трагічно: на чужині вона зазнає тяжких принижень і страждань, втрачає любов. Проте, долаючи злобу, чвари, інтриги імператорського двору, Євпраксія дістається рідної землі.",
  "shortDescription": "Події в романі відбуваються на межі ХІ — ХІІ століть. Внучка Ярослава Мудрого київська княжна Євпраксія виходить заміж за Генріха ІV і стає германською імператрицею. Але ж доля молодої жінки складаєть",
  "coverImage": "/covers/yevpraksiya-11726.jpg",
  "files": [
    {
      "format": "epub",
      "filename": "yevpraksiya-11726__Yevpraksiia.epub",
      "fileDir": "Є",
      "sizeMb": 0.6
    },
    {
      "format": "fb2",
      "filename": "yevpraksiya-11726__Yevpraksiia__yevpraksiya.fb2",
      "fileDir": "Є",
      "sizeMb": 1.2
    }
  ],
  "isFeatured": false,
  "isNewArrival": false,
  "downloadCount": 0,
  "rating": 0,
  "addedAt": "2024-01-01"
}