{
  "id": "zhorstoke-nebo-4439",
  "slug": "zhorstoke-nebo-4439",
  "title": "Жорстоке небо",
  "author": "Макс Кідрук",
  "category": "literature-ukr",
  "language": "uk",
  "year": null,
  "description": "Коли небо не відпускає… Перед вильотом з Парижа пілота українського літака «ААРОН 44» переслідували погані передчуття. Інтуїція підказувала відмовитися від рейсу. Але попри все політ мав відбутися… Для вивчення місця трагедії та з’ясування причин катастрофи «сорокчетвірки» прибула донька його конструктора, Діана Столяр. Загибель літака поставила під сумнів саме існування компанії-виробника. Дівчина намагається будь-що дізнатися правду та розкрити таємницю авіакатастрофи, не здогадуючись, що розслідування може обійтися їй надто дорого…",
  "shortDescription": "Коли небо не відпускає… Перед вильотом з Парижа пілота українського літака «ААРОН 44» переслідували погані передчуття. Інтуїція підказувала відмовитися від рейсу. Але попри все політ мав відбутися… Дл",
  "coverImage": "/covers/placeholder.jpg",
  "files": [
    {
      "format": "epub",
      "filename": "zhorstoke-nebo-4439__Zhorstoke_nebo.epub",
      "fileDir": "Ж",
      "sizeMb": 2.9
    },
    {
      "format": "fb2",
      "filename": "zhorstoke-nebo-4439__Zhorstoke_nebo__zhorstoke-nebo.fb2",
      "fileDir": "Ж",
      "sizeMb": 4.7
    }
  ],
  "isFeatured": false,
  "isNewArrival": false,
  "downloadCount": 0,
  "rating": 0,
  "addedAt": "2024-01-01",
  "subcategory": "detectives",
  "categoryConfidence": "high"
}